pypulse/__init__.py
pypulse/aux_functions.py
pypulse/pulses.py
pypulse/pypulse.py
pypulse_unal-0.1.0.dist-info/METADATA
pypulse_unal-0.1.0.dist-info/WHEEL
pypulse_unal-0.1.0.dist-info/top_level.txt
pypulse_unal-0.1.0.dist-info/RECORD
