Metadata-Version: 2.4
Name: pypulse_unal
Version: 0.1.0
Summary: A Python library for pulse analysis.
Home-page: https://gitlab.com/jsierraj/pypulse
Author: Juan Sierra, Juan Ardila
Author-email: juansesierra54@gmail.com
License: : OSI Approved :: MIT License
Requires-Python: >=3.8
